MIGA/GenerationsAfterFeasibility.py
MIGA/MINSGA3.py
MIGA/__init__.py
MINSGA3-1.1.dist-info/LICENSE
MINSGA3-1.1.dist-info/METADATA
MINSGA3-1.1.dist-info/WHEEL
MINSGA3-1.1.dist-info/top_level.txt
MINSGA3-1.1.dist-info/RECORD
